CCankaoshouceDiyiBufen20171220/README.md
CCankaoshouceDiyiBufen20171220/__init__.py
CCankaoshouceDiyiBufen20171220/__main__.py
CCankaoshouceDiyiBufen20171220/file.epub
CCankaoshouceDiyiBufen20171220/index.html
CCankaoshouceDiyiBufen20171220/css/__init__.py
CCankaoshouceDiyiBufen20171220/css/annotations.css
CCankaoshouceDiyiBufen20171220/css/main.css
CCankaoshouceDiyiBufen20171220/css/normalize.css
CCankaoshouceDiyiBufen20171220/css/popup.css
CCankaoshouceDiyiBufen20171220/font/__init__.py
CCankaoshouceDiyiBufen20171220/font/fontello.eot
CCankaoshouceDiyiBufen20171220/font/fontello.svg
CCankaoshouceDiyiBufen20171220/font/fontello.ttf
CCankaoshouceDiyiBufen20171220/font/fontello.woff
CCankaoshouceDiyiBufen20171220/img/__init__.py
CCankaoshouceDiyiBufen20171220/img/annotator-glyph-sprite.png
CCankaoshouceDiyiBufen20171220/img/annotator-icon-sprite.png
CCankaoshouceDiyiBufen20171220/img/apple-touch-icon.png
CCankaoshouceDiyiBufen20171220/img/cancelfullscreen.png
CCankaoshouceDiyiBufen20171220/img/close.png
CCankaoshouceDiyiBufen20171220/img/fullscreen.png
CCankaoshouceDiyiBufen20171220/img/loader.gif
CCankaoshouceDiyiBufen20171220/img/menu-icon.png
CCankaoshouceDiyiBufen20171220/img/save.png
CCankaoshouceDiyiBufen20171220/img/saved.png
CCankaoshouceDiyiBufen20171220/img/settings-s.png
CCankaoshouceDiyiBufen20171220/img/settings.png
CCankaoshouceDiyiBufen20171220/img/star.png
CCankaoshouceDiyiBufen20171220/js/__init__.py
CCankaoshouceDiyiBufen20171220/js/epub.js
CCankaoshouceDiyiBufen20171220/js/epub.min.js
CCankaoshouceDiyiBufen20171220/js/epub.min.map
CCankaoshouceDiyiBufen20171220/js/hooks.min.js
CCankaoshouceDiyiBufen20171220/js/hooks.min.map
CCankaoshouceDiyiBufen20171220/js/reader.js
CCankaoshouceDiyiBufen20171220/js/reader.js.map
CCankaoshouceDiyiBufen20171220/js/reader.min.js
CCankaoshouceDiyiBufen20171220/js/reader.min.map
CCankaoshouceDiyiBufen20171220/js/hooks/__init__.py
CCankaoshouceDiyiBufen20171220/js/hooks/extensions/__init__.py
c_cankaoshouce_diyi_bufen_2017_12_20-2024.3.2.0.dist-info/METADATA
c_cankaoshouce_diyi_bufen_2017_12_20-2024.3.2.0.dist-info/WHEEL
c_cankaoshouce_diyi_bufen_2017_12_20-2024.3.2.0.dist-info/entry_points.txt
c_cankaoshouce_diyi_bufen_2017_12_20-2024.3.2.0.dist-info/top_level.txt
c_cankaoshouce_diyi_bufen_2017_12_20-2024.3.2.0.dist-info/RECORD
